<?xml version="1.0" encoding="UTF-8"?>
<level gameMode="2">
  <name>lightning4</name>
  <countdown>60</countdown>
  <playableBullpen>
    <piece0>
      <point0>
        <row>0</row>
        <column>0</column>
      </point0>
      <point1>
        <row>1</row>
        <column>0</column>
      </point1>
      <point2>
        <row>2</row>
        <column>0</column>
      </point2>
      <point3>
        <row>0</row>
        <column>1</column>
      </point3>
      <point4>
        <row>0</row>
        <column>2</column>
      </point4>
      <point5>
        <row>1</row>
        <column>1</column>
      </point5>
    </piece0>
    <piece1>
      <point0>
        <row>0</row>
        <column>0</column>
      </point0>
      <point1>
        <row>1</row>
        <column>0</column>
      </point1>
      <point2>
        <row>2</row>
        <column>0</column>
      </point2>
      <point3>
        <row>0</row>
        <column>1</column>
      </point3>
      <point4>
        <row>0</row>
        <column>2</column>
      </point4>
      <point5>
        <row>1</row>
        <column>1</column>
      </point5>
    </piece1>
    <piece2>
      <point0>
        <row>0</row>
        <column>0</column>
      </point0>
      <point1>
        <row>1</row>
        <column>0</column>
      </point1>
      <point2>
        <row>2</row>
        <column>0</column>
      </point2>
      <point3>
        <row>0</row>
        <column>1</column>
      </point3>
      <point4>
        <row>0</row>
        <column>2</column>
      </point4>
      <point5>
        <row>1</row>
        <column>1</column>
      </point5>
    </piece2>
    <piece3>
      <point0>
        <row>0</row>
        <column>0</column>
      </point0>
      <point1>
        <row>1</row>
        <column>0</column>
      </point1>
      <point2>
        <row>2</row>
        <column>0</column>
      </point2>
      <point3>
        <row>0</row>
        <column>1</column>
      </point3>
      <point4>
        <row>0</row>
        <column>2</column>
      </point4>
      <point5>
        <row>1</row>
        <column>1</column>
      </point5>
    </piece3>
    <piece4>
      <point0>
        <row>0</row>
        <column>0</column>
      </point0>
      <point1>
        <row>1</row>
        <column>0</column>
      </point1>
      <point2>
        <row>2</row>
        <column>0</column>
      </point2>
      <point3>
        <row>0</row>
        <column>1</column>
      </point3>
      <point4>
        <row>0</row>
        <column>2</column>
      </point4>
      <point5>
        <row>1</row>
        <column>1</column>
      </point5>
    </piece4>
    <piece5>
      <point0>
        <row>0</row>
        <column>0</column>
      </point0>
      <point1>
        <row>1</row>
        <column>0</column>
      </point1>
      <point2>
        <row>2</row>
        <column>0</column>
      </point2>
      <point3>
        <row>0</row>
        <column>1</column>
      </point3>
      <point4>
        <row>0</row>
        <column>2</column>
      </point4>
      <point5>
        <row>1</row>
        <column>1</column>
      </point5>
    </piece5>
    <piece6>
      <point0>
        <row>0</row>
        <column>0</column>
      </point0>
      <point1>
        <row>1</row>
        <column>0</column>
      </point1>
      <point2>
        <row>2</row>
        <column>0</column>
      </point2>
      <point3>
        <row>0</row>
        <column>1</column>
      </point3>
      <point4>
        <row>0</row>
        <column>2</column>
      </point4>
      <point5>
        <row>1</row>
        <column>1</column>
      </point5>
    </piece6>
    <piece7>
      <point0>
        <row>0</row>
        <column>0</column>
      </point0>
      <point1>
        <row>1</row>
        <column>0</column>
      </point1>
      <point2>
        <row>2</row>
        <column>0</column>
      </point2>
      <point3>
        <row>0</row>
        <column>1</column>
      </point3>
      <point4>
        <row>0</row>
        <column>2</column>
      </point4>
      <point5>
        <row>1</row>
        <column>1</column>
      </point5>
    </piece7>
    <piece8>
      <point0>
        <row>0</row>
        <column>0</column>
      </point0>
      <point1>
        <row>1</row>
        <column>0</column>
      </point1>
      <point2>
        <row>2</row>
        <column>0</column>
      </point2>
      <point3>
        <row>0</row>
        <column>1</column>
      </point3>
      <point4>
        <row>0</row>
        <column>2</column>
      </point4>
      <point5>
        <row>1</row>
        <column>1</column>
      </point5>
    </piece8>
    <piece9>
      <point0>
        <row>0</row>
        <column>0</column>
      </point0>
      <point1>
        <row>1</row>
        <column>0</column>
      </point1>
      <point2>
        <row>2</row>
        <column>0</column>
      </point2>
      <point3>
        <row>0</row>
        <column>1</column>
      </point3>
      <point4>
        <row>0</row>
        <column>2</column>
      </point4>
      <point5>
        <row>1</row>
        <column>1</column>
      </point5>
    </piece9>
  </playableBullpen>
  <board>
    <square0 type="lightning" />
    <square1 type="lightning" />
    <square2 type="lightning" />
    <square3 type="lightning" />
    <square4 type="lightning" />
    <square5 type="lightning" />
    <square6 type="lightning" />
    <square7 type="lightning" />
    <square8 type="lightning" />
    <square9 type="lightning" />
    <square10 type="lightning" />
    <square11 type="lightning" />
    <square12 type="lightning" />
    <square13 type="lightning" />
    <square14 type="lightning" />
    <square15 type="lightning" />
    <square16 type="lightning" />
    <square17 type="lightning" />
    <square18 type="lightning" />
    <square19 type="lightning" />
    <square20 type="lightning" />
    <square21 type="lightning" />
    <square22 type="lightning" />
    <square23 type="lightning" />
    <square24 type="lightning" />
    <square25 type="lightning" />
    <square26 type="lightning" />
    <square27 type="lightning" />
    <square28 type="lightning" />
    <square29 type="lightning" />
    <square30 type="lightning" />
    <square31 type="lightning" />
    <square32 type="lightning" />
    <square33 type="lightning" />
    <square34 type="lightning" />
    <square35 type="lightning" />
    <square36 type="lightning" />
    <square37 type="lightning" />
    <square38 type="lightning" />
    <square39 type="lightning" />
    <square40 type="lightning" />
    <square41 type="lightning" />
    <square42 type="lightning" />
    <square43 type="lightning" />
    <square44 type="lightning" />
    <square45 type="lightning" />
    <square46 type="lightning" />
    <square47 type="lightning" />
    <square48 type="lightning" />
    <square49 type="lightning" />
    <square50 type="lightning" />
    <square51 type="lightning" />
    <square52 type="lightning" />
    <square53 type="lightning" />
    <square54 type="lightning" />
    <square55 type="lightning" />
    <square56 type="lightning" />
    <square57 type="lightning" />
    <square58 type="lightning" />
    <square59 type="lightning" />
    <square60 type="lightning" />
    <square61 type="lightning" />
    <square62 type="lightning" />
    <square63 type="lightning" />
    <square64 type="lightning" />
    <square65 type="lightning" />
    <square66 type="lightning" />
    <square67 type="lightning" />
    <square68 type="lightning" />
    <square69 type="lightning" />
    <square70 type="lightning" />
    <square71 type="lightning" />
    <square72 type="lightning" />
    <square73 type="lightning" />
    <square74 type="lightning" />
    <square75 type="lightning" />
    <square76 type="lightning" />
    <square77 type="lightning" />
    <square78 type="lightning" />
    <square79 type="lightning" />
    <square80 type="lightning" />
    <square81 type="lightning" />
    <square82 type="lightning" />
    <square83 type="lightning" />
    <square84 type="lightning" />
    <square85 type="lightning" />
    <square86 type="lightning" />
    <square87 type="lightning" />
    <square88 type="lightning" />
    <square89 type="lightning" />
    <square90 type="lightning" />
    <square91 type="lightning" />
    <square92 type="lightning" />
    <square93 type="lightning" />
    <square94 type="lightning" />
    <square95 type="lightning" />
    <square96 type="lightning" />
    <square97 type="lightning" />
    <square98 type="lightning" />
    <square99 type="lightning" />
    <square100 type="lightning" />
    <square101 type="lightning" />
    <square102 type="lightning" />
    <square103 type="lightning" />
    <square104 type="lightning" />
    <square105 type="lightning" />
    <square106 type="lightning" />
    <square107 type="lightning" />
    <square108 type="lightning" />
    <square109 type="lightning" />
    <square110 type="lightning" />
    <square111 type="lightning" />
    <square112 type="lightning" />
    <square113 type="lightning" />
    <square114 type="lightning" />
    <square115 type="lightning" />
    <square116 type="lightning" />
    <square117 type="lightning" />
    <square118 type="lightning" />
    <square119 type="lightning" />
    <square120 type="lightning" />
    <square121 type="lightning" />
    <square122 type="lightning" />
    <square123 type="lightning" />
    <square124 type="lightning" />
    <square125 type="lightning" />
    <square126 type="lightning" />
    <square127 type="lightning" />
    <square128 type="lightning" />
    <square129 type="lightning" />
    <square130 type="lightning" />
    <square131 type="lightning" />
    <square132 type="lightning" />
    <square133 type="lightning" />
    <square134 type="lightning" />
    <square135 type="lightning" />
    <square136 type="lightning" />
    <square137 type="lightning" />
    <square138 type="lightning" />
    <square139 type="lightning" />
    <square140 type="lightning" />
    <square141 type="lightning" />
    <square142 type="lightning" />
    <square143 type="lightning" />
  </board>
  <isCustom>false</isCustom>
  <isAddedToPlayer>true</isAddedToPlayer>
</level>
